dandori/__init__.py
dandori/__main__.py
dandori/config.py
dandori/context.py
dandori/env.py
dandori/exception.py
dandori/gh.py
dandori/git.py
dandori/log.py
dandori/ops.py
dandori/process.py
dandori/response.py
dandori/run.py
dandori-0.1.26.dist-info/entry_points.txt
dandori-0.1.26.dist-info/LICENSE
dandori-0.1.26.dist-info/WHEEL
dandori-0.1.26.dist-info/METADATA
dandori-0.1.26.dist-info/RECORD
