Metadata-Version: 2.1
Name: dandori
Version: 0.1.26
Summary: GitHub Actions with Python
Home-page: https://github.com/roy-ht/dandori
License: MIT
Keywords: Continuous Integration,GitHub Actions,Automation,Workflow
Author: Hiroyuki Tanaka
Author-email: aflc0x@gmail.com
Requires-Python: >=3.7,<4.0
Classifier: Development Status :: 2 - Pre-Alpha
Classifier: License :: OSI Approved :: MIT License
Classifier: Programming Language :: Python :: 3
Classifier: Programming Language :: Python :: 3.10
Classifier: Programming Language :: Python :: 3.7
Classifier: Programming Language :: Python :: 3.8
Classifier: Programming Language :: Python :: 3.9
Requires-Dist: ghapi (>=0.1.17,<0.2.0)
Requires-Dist: python-box (>=5.3.0,<6.0.0)
Requires-Dist: ruamel.yaml (>=0.17.10,<0.18.0)
Requires-Dist: toml (>=0.10.2,<0.11.0)
Project-URL: Repository, https://github.com/roy-ht/dandori
